keepasste.py
keepasste-0.2.0.dist-info/METADATA
keepasste-0.2.0.dist-info/WHEEL
keepasste-0.2.0.dist-info/entry_points.txt
keepasste-0.2.0.dist-info/RECORD
